FoxDotUnderline/__init__.py
foxdotunderline-0.1.1.dist-info/METADATA
foxdotunderline-0.1.1.dist-info/WHEEL
foxdotunderline-0.1.1.dist-info/licenses/LICENSE
foxdotunderline-0.1.1.dist-info/RECORD
