Metadata-Version: 2.4
Name: FoxDotUnderline
Version: 0.1.1
Summary: Stop through the underline, e.g. _d1 >> bass()
License-Expression: CC-BY-SA-4.0
License-File: LICENSE
Author: taconi
Author-email: igor.taconi@protonmail.com
Requires-Python: ~=3.11
Classifier: Development Status :: 4 - Beta
Classifier: Intended Audience :: Developers
Classifier: Programming Language :: Python
Classifier: Programming Language :: Python :: 3
Classifier: Programming Language :: Python :: 3.11
Classifier: Programming Language :: Python :: 3.12
Classifier: Programming Language :: Python :: 3.13
Classifier: Programming Language :: Python :: 3.14
